signalr_aio/__init__.py
signalr_aio/_connection.py
signalr_aio/events/__init__.py
signalr_aio/events/_events.py
signalr_aio/hubs/__init__.py
signalr_aio/hubs/_hub.py
signalr_aio/transports/__init__.py
signalr_aio/transports/_exceptions.py
signalr_aio/transports/_parameters.py
signalr_aio/transports/_queue_events.py
signalr_aio/transports/_transport.py
signalr_client_aio-0.0.1.6.2.dist-info/DESCRIPTION.rst
signalr_client_aio-0.0.1.6.2.dist-info/METADATA
signalr_client_aio-0.0.1.6.2.dist-info/RECORD
signalr_client_aio-0.0.1.6.2.dist-info/WHEEL
signalr_client_aio-0.0.1.6.2.dist-info/metadata.json
signalr_client_aio-0.0.1.6.2.dist-info/top_level.txt
