Metadata-Version: 1.1
Name: signalr-client-aio
Version: 0.0.1.6.2
Summary: Simple python SignalR client using asyncio.
Home-page: https://github.com/slazarov/python-signalr-client
Author: Stanislav Lazarov
Author-email: s.a.lazarov@gmail.com
License: MIT
Download-URL: https://github.com/slazarov/python-signalr-client.git
Keywords: signalr,sginalr-weboscket,signalr-client,signalr-asyncio,signalr-aio
Platform: UNKNOWN
Classifier: Development Status :: 3 - Alpha
Classifier: Intended Audience :: Developers
Classifier: Intended Audience :: Information Technology
Classifier: Topic :: Software Development :: Libraries :: Python Modules
Classifier: License :: OSI Approved :: MIT License
Classifier: Programming Language :: Python :: 3.4
Classifier: Programming Language :: Python :: 3.5
Classifier: Programming Language :: Python :: 3.6
